digikamdb/__init__.py
digikamdb/_version.py
digikamdb/albumroots.py
digikamdb/albums.py
digikamdb/conn.py
digikamdb/exceptions.py
digikamdb/image_comments.py
digikamdb/image_helpers.py
digikamdb/images.py
digikamdb/properties.py
digikamdb/settings.py
digikamdb/table.py
digikamdb/tags.py
digikamdb/types.py
Digikam_DB-0.3.5.dist-info/LICENSE
Digikam_DB-0.3.5.dist-info/METADATA
Digikam_DB-0.3.5.dist-info/WHEEL
Digikam_DB-0.3.5.dist-info/top_level.txt
Digikam_DB-0.3.5.dist-info/RECORD
