Metadata-Version: 2.2
Name: Digikam-DB
Version: 0.3.5
Summary: Library to access Digikam metadata
Author-email: rcw-2 <mail@rcw-2.de>
Project-URL: documentation, https://digikam-db.readthedocs.io
Project-URL: homepage, https://github.com/rcw-2/python-digikamdb
Keywords: digikam
Classifier: Development Status :: 3 - Alpha
Classifier: Intended Audience :: Developers
Classifier: License :: OSI Approved :: MIT License
Classifier: Programming Language :: Python :: 3
Classifier: Topic :: Multimedia :: Graphics
Classifier: Topic :: Software Development :: Libraries :: Python Modules
Requires-Python: >=3.7
License-File: LICENSE
Requires-Dist: sqlalchemy>=1.4
Provides-Extra: docs
Requires-Dist: sphinx; extra == "docs"
Requires-Dist: tomli; python_version < "3.11" and extra == "docs"
Provides-Extra: mysql
Requires-Dist: pymysql; extra == "mysql"
